LICENCE
MANIFEST.in
README.md
setup.py
rdfchangesets/__init__.py
rdfchangesets.egg-info/PKG-INFO
rdfchangesets.egg-info/SOURCES.txt
rdfchangesets.egg-info/dependency_links.txt
rdfchangesets.egg-info/top_level.txt